README
setup.py
foursquare.pants.changed.egg-info/PKG-INFO
foursquare.pants.changed.egg-info/SOURCES.txt
foursquare.pants.changed.egg-info/dependency_links.txt
foursquare.pants.changed.egg-info/entry_points.txt
foursquare.pants.changed.egg-info/namespace_packages.txt
foursquare.pants.changed.egg-info/top_level.txt
foursquare/pants/changed/__init__.py
foursquare/pants/changed/lazy_source_mapper.py
foursquare/pants/changed/register.py
foursquare/pants/changed/tasks.py