Metadata-Version: 1.1
Name: foursquare.pants.changed
Version: 0.0.1
Summary: List, build or test locally changed targets
Home-page: https://github.com/foursquare/pants-changed
Author: Foursquare
Author-email: pants@foursquare.com
License: UNKNOWN
Download-URL: https://github.com/foursquare/pants-changed/tags/v0.0.1
Keywords: pantsbuild,pantsbuild plugin
Platform: UNKNOWN
